liupengcheng_mcp_demo/__init__.py
liupengcheng_mcp_demo-0.1.0.dist-info/METADATA
liupengcheng_mcp_demo-0.1.0.dist-info/WHEEL
liupengcheng_mcp_demo-0.1.0.dist-info/entry_points.txt
liupengcheng_mcp_demo-0.1.0.dist-info/RECORD
